Metadata-Version: 2.1
Name: etcd3
Version: 0.8.1
Summary: Python client for the etcd3 API
Home-page: https://github.com/kragniz/python-etcd3
Author: Louis Taylor
Author-email: louis@kragniz.eu
License: Apache Software License 2.0
Keywords: etcd3
Platform: UNKNOWN
Classifier: Development Status :: 2 - Pre-Alpha
Classifier: Intended Audience :: Developers
Classifier: License :: OSI Approved :: Apache Software License
Classifier: Natural Language :: English
Classifier: Programming Language :: Python :: 2
Classifier: Programming Language :: Python :: 2.7
Classifier: Programming Language :: Python :: 3
Classifier: Programming Language :: Python :: 3.4
Classifier: Programming Language :: Python :: 3.5
Classifier: Programming Language :: Python :: 3.6
Requires-Dist: grpcio (>=1.2.0)
Requires-Dist: tenacity (>=4.10.0)
Requires-Dist: protobuf (>=3.5.2.post1)
